{
  "meta": {
    "source": "syringe.dmi",
    "size": {
      "w": 32,
      "h": 32
    },
    "image": "syringe.png"
  },
  "states": {
    "0": {
      "loop": false,
      "directions": {
        "default": [
          {
            "x": 0,
            "y": 0,
            "w": 32,
            "h": 32,
            "delay_ms": 100
          }
        ]
      }
    },
    "1": {
      "loop": false,
      "directions": {
        "default": [
          {
            "x": 32,
            "y": 0,
            "w": 32,
            "h": 32,
            "delay_ms": 100
          }
        ]
      }
    },
    "5": {
      "loop": false,
      "directions": {
        "default": [
          {
            "x": 64,
            "y": 0,
            "w": 32,
            "h": 32,
            "delay_ms": 100
          }
        ]
      }
    },
    "10": {
      "loop": false,
      "directions": {
        "default": [
          {
            "x": 96,
            "y": 0,
            "w": 32,
            "h": 32,
            "delay_ms": 100
          }
        ]
      }
    },
    "15": {
      "loop": false,
      "directions": {
        "default": [
          {
            "x": 128,
            "y": 0,
            "w": 32,
            "h": 32,
            "delay_ms": 100
          }
        ]
      }
    },
    "draw": {
      "loop": false,
      "directions": {
        "default": [
          {
            "x": 160,
            "y": 0,
            "w": 32,
            "h": 32,
            "delay_ms": 100
          }
        ]
      }
    },
    "inject": {
      "loop": false,
      "directions": {
        "default": [
          {
            "x": 192,
            "y": 0,
            "w": 32,
            "h": 32,
            "delay_ms": 100
          }
        ]
      }
    },
    "borghypo": {
      "loop": false,
      "directions": {
        "default": [
          {
            "x": 224,
            "y": 0,
            "w": 32,
            "h": 32,
            "delay_ms": 100
          }
        ]
      }
    },
    "borghypo_s": {
      "loop": false,
      "directions": {
        "default": [
          {
            "x": 0,
            "y": 32,
            "w": 32,
            "h": 32,
            "delay_ms": 100
          }
        ]
      }
    },
    "lazarus_hypo": {
      "loop": false,
      "directions": {
        "default": [
          {
            "x": 32,
            "y": 32,
            "w": 32,
            "h": 32,
            "delay_ms": 100.0
          },
          {
            "x": 64,
            "y": 32,
            "w": 32,
            "h": 32,
            "delay_ms": 100.0
          },
          {
            "x": 96,
            "y": 32,
            "w": 32,
            "h": 32,
            "delay_ms": 100.0
          },
          {
            "x": 128,
            "y": 32,
            "w": 32,
            "h": 32,
            "delay_ms": 100.0
          }
        ]
      }
    },
    "lazarus_empty": {
      "loop": false,
      "directions": {
        "default": [
          {
            "x": 160,
            "y": 32,
            "w": 32,
            "h": 32,
            "delay_ms": 100
          }
        ]
      }
    },
    "hypo": {
      "loop": false,
      "directions": {
        "default": [
          {
            "x": 192,
            "y": 32,
            "w": 32,
            "h": 32,
            "delay_ms": 100
          }
        ]
      }
    },
    "combat_hypo": {
      "loop": false,
      "directions": {
        "default": [
          {
            "x": 224,
            "y": 32,
            "w": 32,
            "h": 32,
            "delay_ms": 100
          }
        ]
      }
    },
    "nanite_hypo": {
      "loop": false,
      "directions": {
        "default": [
          {
            "x": 0,
            "y": 64,
            "w": 32,
            "h": 32,
            "delay_ms": 300.0
          },
          {
            "x": 32,
            "y": 64,
            "w": 32,
            "h": 32,
            "delay_ms": 300.0
          },
          {
            "x": 64,
            "y": 64,
            "w": 32,
            "h": 32,
            "delay_ms": 300.0
          },
          {
            "x": 96,
            "y": 64,
            "w": 32,
            "h": 32,
            "delay_ms": 300.0
          }
        ]
      }
    },
    "nanite_hypo0": {
      "loop": false,
      "directions": {
        "default": [
          {
            "x": 128,
            "y": 64,
            "w": 32,
            "h": 32,
            "delay_ms": 100
          }
        ]
      }
    },
    "holy_hypo": {
      "loop": false,
      "directions": {
        "default": [
          {
            "x": 160,
            "y": 64,
            "w": 32,
            "h": 32,
            "delay_ms": 100
          }
        ]
      }
    },
    "medipen": {
      "loop": false,
      "directions": {
        "default": [
          {
            "x": 192,
            "y": 64,
            "w": 32,
            "h": 32,
            "delay_ms": 100
          }
        ]
      }
    },
    "firstaid": {
      "loop": false,
      "directions": {
        "default": [
          {
            "x": 224,
            "y": 64,
            "w": 32,
            "h": 32,
            "delay_ms": 100
          }
        ]
      }
    },
    "firstaid0": {
      "loop": false,
      "directions": {
        "default": [
          {
            "x": 0,
            "y": 96,
            "w": 32,
            "h": 32,
            "delay_ms": 100
          }
        ]
      }
    },
    "hypovolemic": {
      "loop": false,
      "directions": {
        "default": [
          {
            "x": 32,
            "y": 96,
            "w": 32,
            "h": 32,
            "delay_ms": 100
          }
        ]
      }
    },
    "hypovolemic0": {
      "loop": false,
      "directions": {
        "default": [
          {
            "x": 64,
            "y": 96,
            "w": 32,
            "h": 32,
            "delay_ms": 100
          }
        ]
      }
    },
    "medipen0": {
      "loop": false,
      "directions": {
        "default": [
          {
            "x": 96,
            "y": 96,
            "w": 32,
            "h": 32,
            "delay_ms": 100
          }
        ]
      }
    },
    "stimpen": {
      "loop": false,
      "directions": {
        "default": [
          {
            "x": 128,
            "y": 96,
            "w": 32,
            "h": 32,
            "delay_ms": 100
          }
        ]
      }
    },
    "stimpen0": {
      "loop": false,
      "directions": {
        "default": [
          {
            "x": 160,
            "y": 96,
            "w": 32,
            "h": 32,
            "delay_ms": 100
          }
        ]
      }
    },
    "syndipen": {
      "loop": false,
      "directions": {
        "default": [
          {
            "x": 192,
            "y": 96,
            "w": 32,
            "h": 32,
            "delay_ms": 100
          }
        ]
      }
    },
    "syndipen0": {
      "loop": false,
      "directions": {
        "default": [
          {
            "x": 224,
            "y": 96,
            "w": 32,
            "h": 32,
            "delay_ms": 300.0
          },
          {
            "x": 0,
            "y": 128,
            "w": 32,
            "h": 32,
            "delay_ms": 300.0
          }
        ]
      }
    },
    "morphen": {
      "loop": false,
      "directions": {
        "default": [
          {
            "x": 32,
            "y": 128,
            "w": 32,
            "h": 32,
            "delay_ms": 100
          }
        ]
      }
    },
    "morphen0": {
      "loop": false,
      "directions": {
        "default": [
          {
            "x": 64,
            "y": 128,
            "w": 32,
            "h": 32,
            "delay_ms": 100
          }
        ]
      }
    },
    "oxapen": {
      "loop": false,
      "directions": {
        "default": [
          {
            "x": 96,
            "y": 128,
            "w": 32,
            "h": 32,
            "delay_ms": 100
          }
        ]
      }
    },
    "oxapen0": {
      "loop": false,
      "directions": {
        "default": [
          {
            "x": 128,
            "y": 128,
            "w": 32,
            "h": 32,
            "delay_ms": 100
          }
        ]
      }
    },
    "penacid": {
      "loop": false,
      "directions": {
        "default": [
          {
            "x": 160,
            "y": 128,
            "w": 32,
            "h": 32,
            "delay_ms": 100
          }
        ]
      }
    },
    "penacid0": {
      "loop": false,
      "directions": {
        "default": [
          {
            "x": 192,
            "y": 128,
            "w": 32,
            "h": 32,
            "delay_ms": 100
          }
        ]
      }
    },
    "salacid": {
      "loop": false,
      "directions": {
        "default": [
          {
            "x": 224,
            "y": 128,
            "w": 32,
            "h": 32,
            "delay_ms": 100
          }
        ]
      }
    },
    "salacid0": {
      "loop": false,
      "directions": {
        "default": [
          {
            "x": 0,
            "y": 160,
            "w": 32,
            "h": 32,
            "delay_ms": 100
          }
        ]
      }
    },
    "salpen": {
      "loop": false,
      "directions": {
        "default": [
          {
            "x": 32,
            "y": 160,
            "w": 32,
            "h": 32,
            "delay_ms": 100
          }
        ]
      }
    },
    "salpen0": {
      "loop": false,
      "directions": {
        "default": [
          {
            "x": 64,
            "y": 160,
            "w": 32,
            "h": 32,
            "delay_ms": 100
          }
        ]
      }
    },
    "tbpen": {
      "loop": false,
      "directions": {
        "default": [
          {
            "x": 96,
            "y": 160,
            "w": 32,
            "h": 32,
            "delay_ms": 100
          }
        ]
      }
    },
    "tbpen1": {
      "loop": false,
      "directions": {
        "default": [
          {
            "x": 128,
            "y": 160,
            "w": 32,
            "h": 32,
            "delay_ms": 300.0
          },
          {
            "x": 160,
            "y": 160,
            "w": 32,
            "h": 32,
            "delay_ms": 300.0
          }
        ]
      }
    },
    "tbpen0": {
      "loop": false,
      "directions": {
        "default": [
          {
            "x": 192,
            "y": 160,
            "w": 32,
            "h": 32,
            "delay_ms": 300.0
          },
          {
            "x": 224,
            "y": 160,
            "w": 32,
            "h": 32,
            "delay_ms": 300.0
          }
        ]
      }
    },
    "atropen": {
      "loop": false,
      "directions": {
        "default": [
          {
            "x": 0,
            "y": 192,
            "w": 32,
            "h": 32,
            "delay_ms": 100
          }
        ]
      }
    },
    "atropen0": {
      "loop": false,
      "directions": {
        "default": [
          {
            "x": 32,
            "y": 192,
            "w": 32,
            "h": 32,
            "delay_ms": 100
          }
        ]
      }
    },
    "snail": {
      "loop": false,
      "directions": {
        "default": [
          {
            "x": 64,
            "y": 192,
            "w": 32,
            "h": 32,
            "delay_ms": 100
          }
        ]
      }
    },
    "snail0": {
      "loop": false,
      "directions": {
        "default": [
          {
            "x": 96,
            "y": 192,
            "w": 32,
            "h": 32,
            "delay_ms": 100
          }
        ]
      }
    },
    "gorillapen": {
      "loop": false,
      "directions": {
        "default": [
          {
            "x": 128,
            "y": 192,
            "w": 32,
            "h": 32,
            "delay_ms": 100
          }
        ]
      }
    },
    "gorillapen0": {
      "loop": false,
      "directions": {
        "default": [
          {
            "x": 160,
            "y": 192,
            "w": 32,
            "h": 32,
            "delay_ms": 100
          }
        ]
      }
    },
    "maintenance": {
      "loop": false,
      "directions": {
        "default": [
          {
            "x": 192,
            "y": 192,
            "w": 32,
            "h": 32,
            "delay_ms": 100
          }
        ]
      }
    },
    "maintenance0": {
      "loop": false,
      "directions": {
        "default": [
          {
            "x": 224,
            "y": 192,
            "w": 32,
            "h": 32,
            "delay_ms": 100
          }
        ]
      }
    },
    "luxpen": {
      "loop": false,
      "directions": {
        "default": [
          {
            "x": 0,
            "y": 224,
            "w": 32,
            "h": 32,
            "delay_ms": 100
          }
        ]
      }
    },
    "luxpen0": {
      "loop": false,
      "directions": {
        "default": [
          {
            "x": 32,
            "y": 224,
            "w": 32,
            "h": 32,
            "delay_ms": 100
          }
        ]
      }
    },
    "sampler": {
      "loop": false,
      "directions": {
        "default": [
          {
            "x": 64,
            "y": 224,
            "w": 32,
            "h": 32,
            "delay_ms": 100
          }
        ]
      }
    }
  }
}