{
  "meta": {
    "source": "actions_slime.dmi",
    "size": {
      "w": 32,
      "h": 32
    },
    "image": "actions_slime.png"
  },
  "states": {
    "slimesplit": {
      "loop": false,
      "directions": {
        "default": [
          {
            "x": 0,
            "y": 0,
            "w": 32,
            "h": 32,
            "delay_ms": 100
          }
        ]
      }
    },
    "slimeswap": {
      "loop": false,
      "directions": {
        "default": [
          {
            "x": 32,
            "y": 0,
            "w": 32,
            "h": 32,
            "delay_ms": 100
          }
        ]
      }
    },
    "slimegrow": {
      "loop": false,
      "directions": {
        "default": [
          {
            "x": 64,
            "y": 0,
            "w": 32,
            "h": 32,
            "delay_ms": 100
          }
        ]
      }
    },
    "slimeeat": {
      "loop": false,
      "directions": {
        "default": [
          {
            "x": 96,
            "y": 0,
            "w": 32,
            "h": 32,
            "delay_ms": 100
          }
        ]
      }
    },
    "slimeheal": {
      "loop": false,
      "directions": {
        "default": [
          {
            "x": 128,
            "y": 0,
            "w": 32,
            "h": 32,
            "delay_ms": 100
          }
        ]
      }
    },
    "slimeconsume": {
      "loop": false,
      "directions": {
        "default": [
          {
            "x": 0,
            "y": 32,
            "w": 32,
            "h": 32,
            "delay_ms": 100
          }
        ]
      }
    },
    "slimeeject": {
      "loop": false,
      "directions": {
        "default": [
          {
            "x": 32,
            "y": 32,
            "w": 32,
            "h": 32,
            "delay_ms": 100
          }
        ]
      }
    },
    "slimeuse1": {
      "loop": false,
      "directions": {
        "default": [
          {
            "x": 64,
            "y": 32,
            "w": 32,
            "h": 32,
            "delay_ms": 100
          }
        ]
      }
    },
    "slimeuse2": {
      "loop": false,
      "directions": {
        "default": [
          {
            "x": 96,
            "y": 32,
            "w": 32,
            "h": 32,
            "delay_ms": 100
          }
        ]
      }
    },
    "send_mind": {
      "loop": false,
      "directions": {
        "default": [
          {
            "x": 128,
            "y": 32,
            "w": 32,
            "h": 32,
            "delay_ms": 100
          }
        ]
      }
    },
    "mindlink": {
      "loop": false,
      "directions": {
        "default": [
          {
            "x": 0,
            "y": 64,
            "w": 32,
            "h": 32,
            "delay_ms": 100
          }
        ]
      }
    },
    "link_speech": {
      "loop": false,
      "directions": {
        "default": [
          {
            "x": 32,
            "y": 64,
            "w": 32,
            "h": 32,
            "delay_ms": 100
          }
        ]
      }
    },
    "": {
      "loop": false,
      "directions": {
        "default": [
          {
            "x": 64,
            "y": 64,
            "w": 32,
            "h": 32,
            "delay_ms": 120.0
          },
          {
            "x": 96,
            "y": 64,
            "w": 32,
            "h": 32,
            "delay_ms": 120.0
          },
          {
            "x": 128,
            "y": 64,
            "w": 32,
            "h": 32,
            "delay_ms": 120.0
          },
          {
            "x": 0,
            "y": 96,
            "w": 32,
            "h": 32,
            "delay_ms": 120.0
          }
        ]
      }
    },
    "consume": {
      "loop": false,
      "directions": {
        "default": [
          {
            "x": 32,
            "y": 96,
            "w": 32,
            "h": 32,
            "delay_ms": 100
          }
        ]
      }
    },
    "metabolic_boost": {
      "loop": false,
      "directions": {
        "default": [
          {
            "x": 64,
            "y": 96,
            "w": 32,
            "h": 32,
            "delay_ms": 100
          }
        ]
      }
    },
    "gel_cocoon": {
      "loop": false,
      "directions": {
        "default": [
          {
            "x": 96,
            "y": 96,
            "w": 32,
            "h": 32,
            "delay_ms": 100
          }
        ]
      }
    },
    "globules": {
      "loop": false,
      "directions": {
        "default": [
          {
            "x": 128,
            "y": 96,
            "w": 32,
            "h": 32,
            "delay_ms": 100
          }
        ]
      }
    }
  }
}