{
  "meta": {
    "source": "moth_markings.dmi",
    "size": {
      "w": 45,
      "h": 34
    },
    "image": "moth_markings.png"
  },
  "states": {
    "reddish_head": {
      "loop": false,
      "directions": {
        "south": [
          {
            "x": 0,
            "y": 0,
            "w": 45,
            "h": 34,
            "delay_ms": 100
          }
        ],
        "north": [
          {
            "x": 45,
            "y": 0,
            "w": 45,
            "h": 34,
            "delay_ms": 100
          }
        ],
        "east": [
          {
            "x": 90,
            "y": 0,
            "w": 45,
            "h": 34,
            "delay_ms": 100
          }
        ],
        "west": [
          {
            "x": 135,
            "y": 0,
            "w": 45,
            "h": 34,
            "delay_ms": 100
          }
        ]
      }
    },
    "reddish_chest": {
      "loop": false,
      "directions": {
        "south": [
          {
            "x": 180,
            "y": 0,
            "w": 45,
            "h": 34,
            "delay_ms": 100
          }
        ],
        "north": [
          {
            "x": 225,
            "y": 0,
            "w": 45,
            "h": 34,
            "delay_ms": 100
          }
        ],
        "east": [
          {
            "x": 270,
            "y": 0,
            "w": 45,
            "h": 34,
            "delay_ms": 100
          }
        ],
        "west": [
          {
            "x": 315,
            "y": 0,
            "w": 45,
            "h": 34,
            "delay_ms": 100
          }
        ]
      }
    },
    "reddish_r_arm": {
      "loop": false,
      "directions": {
        "south": [
          {
            "x": 360,
            "y": 0,
            "w": 45,
            "h": 34,
            "delay_ms": 100
          }
        ],
        "north": [
          {
            "x": 405,
            "y": 0,
            "w": 45,
            "h": 34,
            "delay_ms": 100
          }
        ],
        "east": [
          {
            "x": 450,
            "y": 0,
            "w": 45,
            "h": 34,
            "delay_ms": 100
          }
        ],
        "west": [
          {
            "x": 495,
            "y": 0,
            "w": 45,
            "h": 34,
            "delay_ms": 100
          }
        ]
      }
    },
    "reddish_l_arm": {
      "loop": false,
      "directions": {
        "south": [
          {
            "x": 540,
            "y": 0,
            "w": 45,
            "h": 34,
            "delay_ms": 100
          }
        ],
        "north": [
          {
            "x": 585,
            "y": 0,
            "w": 45,
            "h": 34,
            "delay_ms": 100
          }
        ],
        "east": [
          {
            "x": 630,
            "y": 0,
            "w": 45,
            "h": 34,
            "delay_ms": 100
          }
        ],
        "west": [
          {
            "x": 675,
            "y": 0,
            "w": 45,
            "h": 34,
            "delay_ms": 100
          }
        ]
      }
    },
    "reddish_r_leg": {
      "loop": false,
      "directions": {
        "south": [
          {
            "x": 0,
            "y": 34,
            "w": 45,
            "h": 34,
            "delay_ms": 100
          }
        ],
        "north": [
          {
            "x": 45,
            "y": 34,
            "w": 45,
            "h": 34,
            "delay_ms": 100
          }
        ],
        "east": [
          {
            "x": 90,
            "y": 34,
            "w": 45,
            "h": 34,
            "delay_ms": 100
          }
        ],
        "west": [
          {
            "x": 135,
            "y": 34,
            "w": 45,
            "h": 34,
            "delay_ms": 100
          }
        ]
      }
    },
    "reddish_l_leg": {
      "loop": false,
      "directions": {
        "south": [
          {
            "x": 180,
            "y": 34,
            "w": 45,
            "h": 34,
            "delay_ms": 100
          }
        ],
        "north": [
          {
            "x": 225,
            "y": 34,
            "w": 45,
            "h": 34,
            "delay_ms": 100
          }
        ],
        "east": [
          {
            "x": 270,
            "y": 34,
            "w": 45,
            "h": 34,
            "delay_ms": 100
          }
        ],
        "west": [
          {
            "x": 315,
            "y": 34,
            "w": 45,
            "h": 34,
            "delay_ms": 100
          }
        ]
      }
    },
    "royal_head": {
      "loop": false,
      "directions": {
        "south": [
          {
            "x": 360,
            "y": 34,
            "w": 45,
            "h": 34,
            "delay_ms": 100
          }
        ],
        "north": [
          {
            "x": 405,
            "y": 34,
            "w": 45,
            "h": 34,
            "delay_ms": 100
          }
        ],
        "east": [
          {
            "x": 450,
            "y": 34,
            "w": 45,
            "h": 34,
            "delay_ms": 100
          }
        ],
        "west": [
          {
            "x": 495,
            "y": 34,
            "w": 45,
            "h": 34,
            "delay_ms": 100
          }
        ]
      }
    },
    "royal_chest": {
      "loop": false,
      "directions": {
        "south": [
          {
            "x": 540,
            "y": 34,
            "w": 45,
            "h": 34,
            "delay_ms": 100
          }
        ],
        "north": [
          {
            "x": 585,
            "y": 34,
            "w": 45,
            "h": 34,
            "delay_ms": 100
          }
        ],
        "east": [
          {
            "x": 630,
            "y": 34,
            "w": 45,
            "h": 34,
            "delay_ms": 100
          }
        ],
        "west": [
          {
            "x": 675,
            "y": 34,
            "w": 45,
            "h": 34,
            "delay_ms": 100
          }
        ]
      }
    },
    "royal_r_arm": {
      "loop": false,
      "directions": {
        "south": [
          {
            "x": 0,
            "y": 68,
            "w": 45,
            "h": 34,
            "delay_ms": 100
          }
        ],
        "north": [
          {
            "x": 45,
            "y": 68,
            "w": 45,
            "h": 34,
            "delay_ms": 100
          }
        ],
        "east": [
          {
            "x": 90,
            "y": 68,
            "w": 45,
            "h": 34,
            "delay_ms": 100
          }
        ],
        "west": [
          {
            "x": 135,
            "y": 68,
            "w": 45,
            "h": 34,
            "delay_ms": 100
          }
        ]
      }
    },
    "royal_l_arm": {
      "loop": false,
      "directions": {
        "south": [
          {
            "x": 180,
            "y": 68,
            "w": 45,
            "h": 34,
            "delay_ms": 100
          }
        ],
        "north": [
          {
            "x": 225,
            "y": 68,
            "w": 45,
            "h": 34,
            "delay_ms": 100
          }
        ],
        "east": [
          {
            "x": 270,
            "y": 68,
            "w": 45,
            "h": 34,
            "delay_ms": 100
          }
        ],
        "west": [
          {
            "x": 315,
            "y": 68,
            "w": 45,
            "h": 34,
            "delay_ms": 100
          }
        ]
      }
    },
    "royal_r_leg": {
      "loop": false,
      "directions": {
        "south": [
          {
            "x": 360,
            "y": 68,
            "w": 45,
            "h": 34,
            "delay_ms": 100
          }
        ],
        "north": [
          {
            "x": 405,
            "y": 68,
            "w": 45,
            "h": 34,
            "delay_ms": 100
          }
        ],
        "east": [
          {
            "x": 450,
            "y": 68,
            "w": 45,
            "h": 34,
            "delay_ms": 100
          }
        ],
        "west": [
          {
            "x": 495,
            "y": 68,
            "w": 45,
            "h": 34,
            "delay_ms": 100
          }
        ]
      }
    },
    "royal_l_leg": {
      "loop": false,
      "directions": {
        "south": [
          {
            "x": 540,
            "y": 68,
            "w": 45,
            "h": 34,
            "delay_ms": 100
          }
        ],
        "north": [
          {
            "x": 585,
            "y": 68,
            "w": 45,
            "h": 34,
            "delay_ms": 100
          }
        ],
        "east": [
          {
            "x": 630,
            "y": 68,
            "w": 45,
            "h": 34,
            "delay_ms": 100
          }
        ],
        "west": [
          {
            "x": 675,
            "y": 68,
            "w": 45,
            "h": 34,
            "delay_ms": 100
          }
        ]
      }
    },
    "gothic_head": {
      "loop": false,
      "directions": {
        "south": [
          {
            "x": 0,
            "y": 102,
            "w": 45,
            "h": 34,
            "delay_ms": 100
          }
        ],
        "north": [
          {
            "x": 45,
            "y": 102,
            "w": 45,
            "h": 34,
            "delay_ms": 100
          }
        ],
        "east": [
          {
            "x": 90,
            "y": 102,
            "w": 45,
            "h": 34,
            "delay_ms": 100
          }
        ],
        "west": [
          {
            "x": 135,
            "y": 102,
            "w": 45,
            "h": 34,
            "delay_ms": 100
          }
        ]
      }
    },
    "gothic_chest": {
      "loop": false,
      "directions": {
        "south": [
          {
            "x": 180,
            "y": 102,
            "w": 45,
            "h": 34,
            "delay_ms": 100
          }
        ],
        "north": [
          {
            "x": 225,
            "y": 102,
            "w": 45,
            "h": 34,
            "delay_ms": 100
          }
        ],
        "east": [
          {
            "x": 270,
            "y": 102,
            "w": 45,
            "h": 34,
            "delay_ms": 100
          }
        ],
        "west": [
          {
            "x": 315,
            "y": 102,
            "w": 45,
            "h": 34,
            "delay_ms": 100
          }
        ]
      }
    },
    "gothic_r_arm": {
      "loop": false,
      "directions": {
        "south": [
          {
            "x": 360,
            "y": 102,
            "w": 45,
            "h": 34,
            "delay_ms": 100
          }
        ],
        "north": [
          {
            "x": 405,
            "y": 102,
            "w": 45,
            "h": 34,
            "delay_ms": 100
          }
        ],
        "east": [
          {
            "x": 450,
            "y": 102,
            "w": 45,
            "h": 34,
            "delay_ms": 100
          }
        ],
        "west": [
          {
            "x": 495,
            "y": 102,
            "w": 45,
            "h": 34,
            "delay_ms": 100
          }
        ]
      }
    },
    "gothic_l_arm": {
      "loop": false,
      "directions": {
        "south": [
          {
            "x": 540,
            "y": 102,
            "w": 45,
            "h": 34,
            "delay_ms": 100
          }
        ],
        "north": [
          {
            "x": 585,
            "y": 102,
            "w": 45,
            "h": 34,
            "delay_ms": 100
          }
        ],
        "east": [
          {
            "x": 630,
            "y": 102,
            "w": 45,
            "h": 34,
            "delay_ms": 100
          }
        ],
        "west": [
          {
            "x": 675,
            "y": 102,
            "w": 45,
            "h": 34,
            "delay_ms": 100
          }
        ]
      }
    },
    "gothic_r_leg": {
      "loop": false,
      "directions": {
        "south": [
          {
            "x": 0,
            "y": 136,
            "w": 45,
            "h": 34,
            "delay_ms": 100
          }
        ],
        "north": [
          {
            "x": 45,
            "y": 136,
            "w": 45,
            "h": 34,
            "delay_ms": 100
          }
        ],
        "east": [
          {
            "x": 90,
            "y": 136,
            "w": 45,
            "h": 34,
            "delay_ms": 100
          }
        ],
        "west": [
          {
            "x": 135,
            "y": 136,
            "w": 45,
            "h": 34,
            "delay_ms": 100
          }
        ]
      }
    },
    "gothic_l_leg": {
      "loop": false,
      "directions": {
        "south": [
          {
            "x": 180,
            "y": 136,
            "w": 45,
            "h": 34,
            "delay_ms": 100
          }
        ],
        "north": [
          {
            "x": 225,
            "y": 136,
            "w": 45,
            "h": 34,
            "delay_ms": 100
          }
        ],
        "east": [
          {
            "x": 270,
            "y": 136,
            "w": 45,
            "h": 34,
            "delay_ms": 100
          }
        ],
        "west": [
          {
            "x": 315,
            "y": 136,
            "w": 45,
            "h": 34,
            "delay_ms": 100
          }
        ]
      }
    },
    "whitefly_head": {
      "loop": false,
      "directions": {
        "south": [
          {
            "x": 360,
            "y": 136,
            "w": 45,
            "h": 34,
            "delay_ms": 100
          }
        ],
        "north": [
          {
            "x": 405,
            "y": 136,
            "w": 45,
            "h": 34,
            "delay_ms": 100
          }
        ],
        "east": [
          {
            "x": 450,
            "y": 136,
            "w": 45,
            "h": 34,
            "delay_ms": 100
          }
        ],
        "west": [
          {
            "x": 495,
            "y": 136,
            "w": 45,
            "h": 34,
            "delay_ms": 100
          }
        ]
      }
    },
    "whitefly_chest": {
      "loop": false,
      "directions": {
        "south": [
          {
            "x": 540,
            "y": 136,
            "w": 45,
            "h": 34,
            "delay_ms": 100
          }
        ],
        "north": [
          {
            "x": 585,
            "y": 136,
            "w": 45,
            "h": 34,
            "delay_ms": 100
          }
        ],
        "east": [
          {
            "x": 630,
            "y": 136,
            "w": 45,
            "h": 34,
            "delay_ms": 100
          }
        ],
        "west": [
          {
            "x": 675,
            "y": 136,
            "w": 45,
            "h": 34,
            "delay_ms": 100
          }
        ]
      }
    },
    "whitefly_r_arm": {
      "loop": false,
      "directions": {
        "south": [
          {
            "x": 0,
            "y": 170,
            "w": 45,
            "h": 34,
            "delay_ms": 100
          }
        ],
        "north": [
          {
            "x": 45,
            "y": 170,
            "w": 45,
            "h": 34,
            "delay_ms": 100
          }
        ],
        "east": [
          {
            "x": 90,
            "y": 170,
            "w": 45,
            "h": 34,
            "delay_ms": 100
          }
        ],
        "west": [
          {
            "x": 135,
            "y": 170,
            "w": 45,
            "h": 34,
            "delay_ms": 100
          }
        ]
      }
    },
    "whitefly_l_arm": {
      "loop": false,
      "directions": {
        "south": [
          {
            "x": 180,
            "y": 170,
            "w": 45,
            "h": 34,
            "delay_ms": 100
          }
        ],
        "north": [
          {
            "x": 225,
            "y": 170,
            "w": 45,
            "h": 34,
            "delay_ms": 100
          }
        ],
        "east": [
          {
            "x": 270,
            "y": 170,
            "w": 45,
            "h": 34,
            "delay_ms": 100
          }
        ],
        "west": [
          {
            "x": 315,
            "y": 170,
            "w": 45,
            "h": 34,
            "delay_ms": 100
          }
        ]
      }
    },
    "whitefly_r_leg": {
      "loop": false,
      "directions": {
        "south": [
          {
            "x": 360,
            "y": 170,
            "w": 45,
            "h": 34,
            "delay_ms": 100
          }
        ],
        "north": [
          {
            "x": 405,
            "y": 170,
            "w": 45,
            "h": 34,
            "delay_ms": 100
          }
        ],
        "east": [
          {
            "x": 450,
            "y": 170,
            "w": 45,
            "h": 34,
            "delay_ms": 100
          }
        ],
        "west": [
          {
            "x": 495,
            "y": 170,
            "w": 45,
            "h": 34,
            "delay_ms": 100
          }
        ]
      }
    },
    "whitefly_l_leg": {
      "loop": false,
      "directions": {
        "south": [
          {
            "x": 540,
            "y": 170,
            "w": 45,
            "h": 34,
            "delay_ms": 100
          }
        ],
        "north": [
          {
            "x": 585,
            "y": 170,
            "w": 45,
            "h": 34,
            "delay_ms": 100
          }
        ],
        "east": [
          {
            "x": 630,
            "y": 170,
            "w": 45,
            "h": 34,
            "delay_ms": 100
          }
        ],
        "west": [
          {
            "x": 675,
            "y": 170,
            "w": 45,
            "h": 34,
            "delay_ms": 100
          }
        ]
      }
    },
    "burnt_off_head": {
      "loop": false,
      "directions": {
        "south": [
          {
            "x": 0,
            "y": 204,
            "w": 45,
            "h": 34,
            "delay_ms": 100
          }
        ],
        "north": [
          {
            "x": 45,
            "y": 204,
            "w": 45,
            "h": 34,
            "delay_ms": 100
          }
        ],
        "east": [
          {
            "x": 90,
            "y": 204,
            "w": 45,
            "h": 34,
            "delay_ms": 100
          }
        ],
        "west": [
          {
            "x": 135,
            "y": 204,
            "w": 45,
            "h": 34,
            "delay_ms": 100
          }
        ]
      }
    },
    "burnt_off_chest": {
      "loop": false,
      "directions": {
        "south": [
          {
            "x": 180,
            "y": 204,
            "w": 45,
            "h": 34,
            "delay_ms": 100
          }
        ],
        "north": [
          {
            "x": 225,
            "y": 204,
            "w": 45,
            "h": 34,
            "delay_ms": 100
          }
        ],
        "east": [
          {
            "x": 270,
            "y": 204,
            "w": 45,
            "h": 34,
            "delay_ms": 100
          }
        ],
        "west": [
          {
            "x": 315,
            "y": 204,
            "w": 45,
            "h": 34,
            "delay_ms": 100
          }
        ]
      }
    },
    "burnt_off_r_arm": {
      "loop": false,
      "directions": {
        "south": [
          {
            "x": 360,
            "y": 204,
            "w": 45,
            "h": 34,
            "delay_ms": 100
          }
        ],
        "north": [
          {
            "x": 405,
            "y": 204,
            "w": 45,
            "h": 34,
            "delay_ms": 100
          }
        ],
        "east": [
          {
            "x": 450,
            "y": 204,
            "w": 45,
            "h": 34,
            "delay_ms": 100
          }
        ],
        "west": [
          {
            "x": 495,
            "y": 204,
            "w": 45,
            "h": 34,
            "delay_ms": 100
          }
        ]
      }
    },
    "burnt_off_l_arm": {
      "loop": false,
      "directions": {
        "south": [
          {
            "x": 540,
            "y": 204,
            "w": 45,
            "h": 34,
            "delay_ms": 100
          }
        ],
        "north": [
          {
            "x": 585,
            "y": 204,
            "w": 45,
            "h": 34,
            "delay_ms": 100
          }
        ],
        "east": [
          {
            "x": 630,
            "y": 204,
            "w": 45,
            "h": 34,
            "delay_ms": 100
          }
        ],
        "west": [
          {
            "x": 675,
            "y": 204,
            "w": 45,
            "h": 34,
            "delay_ms": 100
          }
        ]
      }
    },
    "burnt_off_r_leg": {
      "loop": false,
      "directions": {
        "south": [
          {
            "x": 0,
            "y": 238,
            "w": 45,
            "h": 34,
            "delay_ms": 100
          }
        ],
        "north": [
          {
            "x": 45,
            "y": 238,
            "w": 45,
            "h": 34,
            "delay_ms": 100
          }
        ],
        "east": [
          {
            "x": 90,
            "y": 238,
            "w": 45,
            "h": 34,
            "delay_ms": 100
          }
        ],
        "west": [
          {
            "x": 135,
            "y": 238,
            "w": 45,
            "h": 34,
            "delay_ms": 100
          }
        ]
      }
    },
    "burnt_off_l_leg": {
      "loop": false,
      "directions": {
        "south": [
          {
            "x": 180,
            "y": 238,
            "w": 45,
            "h": 34,
            "delay_ms": 100
          }
        ],
        "north": [
          {
            "x": 225,
            "y": 238,
            "w": 45,
            "h": 34,
            "delay_ms": 100
          }
        ],
        "east": [
          {
            "x": 270,
            "y": 238,
            "w": 45,
            "h": 34,
            "delay_ms": 100
          }
        ],
        "west": [
          {
            "x": 315,
            "y": 238,
            "w": 45,
            "h": 34,
            "delay_ms": 100
          }
        ]
      }
    },
    "firewatch_head": {
      "loop": false,
      "directions": {
        "south": [
          {
            "x": 360,
            "y": 238,
            "w": 45,
            "h": 34,
            "delay_ms": 100
          }
        ],
        "north": [
          {
            "x": 405,
            "y": 238,
            "w": 45,
            "h": 34,
            "delay_ms": 100
          }
        ],
        "east": [
          {
            "x": 450,
            "y": 238,
            "w": 45,
            "h": 34,
            "delay_ms": 100
          }
        ],
        "west": [
          {
            "x": 495,
            "y": 238,
            "w": 45,
            "h": 34,
            "delay_ms": 100
          }
        ]
      }
    },
    "firewatch_chest": {
      "loop": false,
      "directions": {
        "south": [
          {
            "x": 540,
            "y": 238,
            "w": 45,
            "h": 34,
            "delay_ms": 100
          }
        ],
        "north": [
          {
            "x": 585,
            "y": 238,
            "w": 45,
            "h": 34,
            "delay_ms": 100
          }
        ],
        "east": [
          {
            "x": 630,
            "y": 238,
            "w": 45,
            "h": 34,
            "delay_ms": 100
          }
        ],
        "west": [
          {
            "x": 675,
            "y": 238,
            "w": 45,
            "h": 34,
            "delay_ms": 100
          }
        ]
      }
    },
    "firewatch_r_arm": {
      "loop": false,
      "directions": {
        "south": [
          {
            "x": 0,
            "y": 272,
            "w": 45,
            "h": 34,
            "delay_ms": 100
          }
        ],
        "north": [
          {
            "x": 45,
            "y": 272,
            "w": 45,
            "h": 34,
            "delay_ms": 100
          }
        ],
        "east": [
          {
            "x": 90,
            "y": 272,
            "w": 45,
            "h": 34,
            "delay_ms": 100
          }
        ],
        "west": [
          {
            "x": 135,
            "y": 272,
            "w": 45,
            "h": 34,
            "delay_ms": 100
          }
        ]
      }
    },
    "firewatch_l_arm": {
      "loop": false,
      "directions": {
        "south": [
          {
            "x": 180,
            "y": 272,
            "w": 45,
            "h": 34,
            "delay_ms": 100
          }
        ],
        "north": [
          {
            "x": 225,
            "y": 272,
            "w": 45,
            "h": 34,
            "delay_ms": 100
          }
        ],
        "east": [
          {
            "x": 270,
            "y": 272,
            "w": 45,
            "h": 34,
            "delay_ms": 100
          }
        ],
        "west": [
          {
            "x": 315,
            "y": 272,
            "w": 45,
            "h": 34,
            "delay_ms": 100
          }
        ]
      }
    },
    "firewatch_r_leg": {
      "loop": false,
      "directions": {
        "south": [
          {
            "x": 360,
            "y": 272,
            "w": 45,
            "h": 34,
            "delay_ms": 100
          }
        ],
        "north": [
          {
            "x": 405,
            "y": 272,
            "w": 45,
            "h": 34,
            "delay_ms": 100
          }
        ],
        "east": [
          {
            "x": 450,
            "y": 272,
            "w": 45,
            "h": 34,
            "delay_ms": 100
          }
        ],
        "west": [
          {
            "x": 495,
            "y": 272,
            "w": 45,
            "h": 34,
            "delay_ms": 100
          }
        ]
      }
    },
    "firewatch_l_leg": {
      "loop": false,
      "directions": {
        "south": [
          {
            "x": 540,
            "y": 272,
            "w": 45,
            "h": 34,
            "delay_ms": 100
          }
        ],
        "north": [
          {
            "x": 585,
            "y": 272,
            "w": 45,
            "h": 34,
            "delay_ms": 100
          }
        ],
        "east": [
          {
            "x": 630,
            "y": 272,
            "w": 45,
            "h": 34,
            "delay_ms": 100
          }
        ],
        "west": [
          {
            "x": 675,
            "y": 272,
            "w": 45,
            "h": 34,
            "delay_ms": 100
          }
        ]
      }
    },
    "deathhead_head": {
      "loop": false,
      "directions": {
        "south": [
          {
            "x": 0,
            "y": 306,
            "w": 45,
            "h": 34,
            "delay_ms": 100
          }
        ],
        "north": [
          {
            "x": 45,
            "y": 306,
            "w": 45,
            "h": 34,
            "delay_ms": 100
          }
        ],
        "east": [
          {
            "x": 90,
            "y": 306,
            "w": 45,
            "h": 34,
            "delay_ms": 100
          }
        ],
        "west": [
          {
            "x": 135,
            "y": 306,
            "w": 45,
            "h": 34,
            "delay_ms": 100
          }
        ]
      }
    },
    "deathhead_chest": {
      "loop": false,
      "directions": {
        "south": [
          {
            "x": 180,
            "y": 306,
            "w": 45,
            "h": 34,
            "delay_ms": 100
          }
        ],
        "north": [
          {
            "x": 225,
            "y": 306,
            "w": 45,
            "h": 34,
            "delay_ms": 100
          }
        ],
        "east": [
          {
            "x": 270,
            "y": 306,
            "w": 45,
            "h": 34,
            "delay_ms": 100
          }
        ],
        "west": [
          {
            "x": 315,
            "y": 306,
            "w": 45,
            "h": 34,
            "delay_ms": 100
          }
        ]
      }
    },
    "deathhead_r_arm": {
      "loop": false,
      "directions": {
        "south": [
          {
            "x": 360,
            "y": 306,
            "w": 45,
            "h": 34,
            "delay_ms": 100
          }
        ],
        "north": [
          {
            "x": 405,
            "y": 306,
            "w": 45,
            "h": 34,
            "delay_ms": 100
          }
        ],
        "east": [
          {
            "x": 450,
            "y": 306,
            "w": 45,
            "h": 34,
            "delay_ms": 100
          }
        ],
        "west": [
          {
            "x": 495,
            "y": 306,
            "w": 45,
            "h": 34,
            "delay_ms": 100
          }
        ]
      }
    },
    "deathhead_l_arm": {
      "loop": false,
      "directions": {
        "south": [
          {
            "x": 540,
            "y": 306,
            "w": 45,
            "h": 34,
            "delay_ms": 100
          }
        ],
        "north": [
          {
            "x": 585,
            "y": 306,
            "w": 45,
            "h": 34,
            "delay_ms": 100
          }
        ],
        "east": [
          {
            "x": 630,
            "y": 306,
            "w": 45,
            "h": 34,
            "delay_ms": 100
          }
        ],
        "west": [
          {
            "x": 675,
            "y": 306,
            "w": 45,
            "h": 34,
            "delay_ms": 100
          }
        ]
      }
    },
    "deathhead_r_leg": {
      "loop": false,
      "directions": {
        "south": [
          {
            "x": 0,
            "y": 340,
            "w": 45,
            "h": 34,
            "delay_ms": 100
          }
        ],
        "north": [
          {
            "x": 45,
            "y": 340,
            "w": 45,
            "h": 34,
            "delay_ms": 100
          }
        ],
        "east": [
          {
            "x": 90,
            "y": 340,
            "w": 45,
            "h": 34,
            "delay_ms": 100
          }
        ],
        "west": [
          {
            "x": 135,
            "y": 340,
            "w": 45,
            "h": 34,
            "delay_ms": 100
          }
        ]
      }
    },
    "deathhead_l_leg": {
      "loop": false,
      "directions": {
        "south": [
          {
            "x": 180,
            "y": 340,
            "w": 45,
            "h": 34,
            "delay_ms": 100
          }
        ],
        "north": [
          {
            "x": 225,
            "y": 340,
            "w": 45,
            "h": 34,
            "delay_ms": 100
          }
        ],
        "east": [
          {
            "x": 270,
            "y": 340,
            "w": 45,
            "h": 34,
            "delay_ms": 100
          }
        ],
        "west": [
          {
            "x": 315,
            "y": 340,
            "w": 45,
            "h": 34,
            "delay_ms": 100
          }
        ]
      }
    },
    "poison_head": {
      "loop": false,
      "directions": {
        "south": [
          {
            "x": 360,
            "y": 340,
            "w": 45,
            "h": 34,
            "delay_ms": 100
          }
        ],
        "north": [
          {
            "x": 405,
            "y": 340,
            "w": 45,
            "h": 34,
            "delay_ms": 100
          }
        ],
        "east": [
          {
            "x": 450,
            "y": 340,
            "w": 45,
            "h": 34,
            "delay_ms": 100
          }
        ],
        "west": [
          {
            "x": 495,
            "y": 340,
            "w": 45,
            "h": 34,
            "delay_ms": 100
          }
        ]
      }
    },
    "poison_chest": {
      "loop": false,
      "directions": {
        "south": [
          {
            "x": 540,
            "y": 340,
            "w": 45,
            "h": 34,
            "delay_ms": 100
          }
        ],
        "north": [
          {
            "x": 585,
            "y": 340,
            "w": 45,
            "h": 34,
            "delay_ms": 100
          }
        ],
        "east": [
          {
            "x": 630,
            "y": 340,
            "w": 45,
            "h": 34,
            "delay_ms": 100
          }
        ],
        "west": [
          {
            "x": 675,
            "y": 340,
            "w": 45,
            "h": 34,
            "delay_ms": 100
          }
        ]
      }
    },
    "poison_r_arm": {
      "loop": false,
      "directions": {
        "south": [
          {
            "x": 0,
            "y": 374,
            "w": 45,
            "h": 34,
            "delay_ms": 100
          }
        ],
        "north": [
          {
            "x": 45,
            "y": 374,
            "w": 45,
            "h": 34,
            "delay_ms": 100
          }
        ],
        "east": [
          {
            "x": 90,
            "y": 374,
            "w": 45,
            "h": 34,
            "delay_ms": 100
          }
        ],
        "west": [
          {
            "x": 135,
            "y": 374,
            "w": 45,
            "h": 34,
            "delay_ms": 100
          }
        ]
      }
    },
    "poison_l_arm": {
      "loop": false,
      "directions": {
        "south": [
          {
            "x": 180,
            "y": 374,
            "w": 45,
            "h": 34,
            "delay_ms": 100
          }
        ],
        "north": [
          {
            "x": 225,
            "y": 374,
            "w": 45,
            "h": 34,
            "delay_ms": 100
          }
        ],
        "east": [
          {
            "x": 270,
            "y": 374,
            "w": 45,
            "h": 34,
            "delay_ms": 100
          }
        ],
        "west": [
          {
            "x": 315,
            "y": 374,
            "w": 45,
            "h": 34,
            "delay_ms": 100
          }
        ]
      }
    },
    "poison_r_leg": {
      "loop": false,
      "directions": {
        "south": [
          {
            "x": 360,
            "y": 374,
            "w": 45,
            "h": 34,
            "delay_ms": 100
          }
        ],
        "north": [
          {
            "x": 405,
            "y": 374,
            "w": 45,
            "h": 34,
            "delay_ms": 100
          }
        ],
        "east": [
          {
            "x": 450,
            "y": 374,
            "w": 45,
            "h": 34,
            "delay_ms": 100
          }
        ],
        "west": [
          {
            "x": 495,
            "y": 374,
            "w": 45,
            "h": 34,
            "delay_ms": 100
          }
        ]
      }
    },
    "poison_l_leg": {
      "loop": false,
      "directions": {
        "south": [
          {
            "x": 540,
            "y": 374,
            "w": 45,
            "h": 34,
            "delay_ms": 100
          }
        ],
        "north": [
          {
            "x": 585,
            "y": 374,
            "w": 45,
            "h": 34,
            "delay_ms": 100
          }
        ],
        "east": [
          {
            "x": 630,
            "y": 374,
            "w": 45,
            "h": 34,
            "delay_ms": 100
          }
        ],
        "west": [
          {
            "x": 675,
            "y": 374,
            "w": 45,
            "h": 34,
            "delay_ms": 100
          }
        ]
      }
    },
    "ragged_head": {
      "loop": false,
      "directions": {
        "south": [
          {
            "x": 0,
            "y": 408,
            "w": 45,
            "h": 34,
            "delay_ms": 100
          }
        ],
        "north": [
          {
            "x": 45,
            "y": 408,
            "w": 45,
            "h": 34,
            "delay_ms": 100
          }
        ],
        "east": [
          {
            "x": 90,
            "y": 408,
            "w": 45,
            "h": 34,
            "delay_ms": 100
          }
        ],
        "west": [
          {
            "x": 135,
            "y": 408,
            "w": 45,
            "h": 34,
            "delay_ms": 100
          }
        ]
      }
    },
    "ragged_chest": {
      "loop": false,
      "directions": {
        "south": [
          {
            "x": 180,
            "y": 408,
            "w": 45,
            "h": 34,
            "delay_ms": 100
          }
        ],
        "north": [
          {
            "x": 225,
            "y": 408,
            "w": 45,
            "h": 34,
            "delay_ms": 100
          }
        ],
        "east": [
          {
            "x": 270,
            "y": 408,
            "w": 45,
            "h": 34,
            "delay_ms": 100
          }
        ],
        "west": [
          {
            "x": 315,
            "y": 408,
            "w": 45,
            "h": 34,
            "delay_ms": 100
          }
        ]
      }
    },
    "ragged_r_arm": {
      "loop": false,
      "directions": {
        "south": [
          {
            "x": 360,
            "y": 408,
            "w": 45,
            "h": 34,
            "delay_ms": 100
          }
        ],
        "north": [
          {
            "x": 405,
            "y": 408,
            "w": 45,
            "h": 34,
            "delay_ms": 100
          }
        ],
        "east": [
          {
            "x": 450,
            "y": 408,
            "w": 45,
            "h": 34,
            "delay_ms": 100
          }
        ],
        "west": [
          {
            "x": 495,
            "y": 408,
            "w": 45,
            "h": 34,
            "delay_ms": 100
          }
        ]
      }
    },
    "ragged_l_arm": {
      "loop": false,
      "directions": {
        "south": [
          {
            "x": 540,
            "y": 408,
            "w": 45,
            "h": 34,
            "delay_ms": 100
          }
        ],
        "north": [
          {
            "x": 585,
            "y": 408,
            "w": 45,
            "h": 34,
            "delay_ms": 100
          }
        ],
        "east": [
          {
            "x": 630,
            "y": 408,
            "w": 45,
            "h": 34,
            "delay_ms": 100
          }
        ],
        "west": [
          {
            "x": 675,
            "y": 408,
            "w": 45,
            "h": 34,
            "delay_ms": 100
          }
        ]
      }
    },
    "ragged_r_leg": {
      "loop": false,
      "directions": {
        "south": [
          {
            "x": 0,
            "y": 442,
            "w": 45,
            "h": 34,
            "delay_ms": 100
          }
        ],
        "north": [
          {
            "x": 45,
            "y": 442,
            "w": 45,
            "h": 34,
            "delay_ms": 100
          }
        ],
        "east": [
          {
            "x": 90,
            "y": 442,
            "w": 45,
            "h": 34,
            "delay_ms": 100
          }
        ],
        "west": [
          {
            "x": 135,
            "y": 442,
            "w": 45,
            "h": 34,
            "delay_ms": 100
          }
        ]
      }
    },
    "ragged_l_leg": {
      "loop": false,
      "directions": {
        "south": [
          {
            "x": 180,
            "y": 442,
            "w": 45,
            "h": 34,
            "delay_ms": 100
          }
        ],
        "north": [
          {
            "x": 225,
            "y": 442,
            "w": 45,
            "h": 34,
            "delay_ms": 100
          }
        ],
        "east": [
          {
            "x": 270,
            "y": 442,
            "w": 45,
            "h": 34,
            "delay_ms": 100
          }
        ],
        "west": [
          {
            "x": 315,
            "y": 442,
            "w": 45,
            "h": 34,
            "delay_ms": 100
          }
        ]
      }
    },
    "moonfly_head": {
      "loop": false,
      "directions": {
        "south": [
          {
            "x": 360,
            "y": 442,
            "w": 45,
            "h": 34,
            "delay_ms": 100
          }
        ],
        "north": [
          {
            "x": 405,
            "y": 442,
            "w": 45,
            "h": 34,
            "delay_ms": 100
          }
        ],
        "east": [
          {
            "x": 450,
            "y": 442,
            "w": 45,
            "h": 34,
            "delay_ms": 100
          }
        ],
        "west": [
          {
            "x": 495,
            "y": 442,
            "w": 45,
            "h": 34,
            "delay_ms": 100
          }
        ]
      }
    },
    "moonfly_chest": {
      "loop": false,
      "directions": {
        "south": [
          {
            "x": 540,
            "y": 442,
            "w": 45,
            "h": 34,
            "delay_ms": 100
          }
        ],
        "north": [
          {
            "x": 585,
            "y": 442,
            "w": 45,
            "h": 34,
            "delay_ms": 100
          }
        ],
        "east": [
          {
            "x": 630,
            "y": 442,
            "w": 45,
            "h": 34,
            "delay_ms": 100
          }
        ],
        "west": [
          {
            "x": 675,
            "y": 442,
            "w": 45,
            "h": 34,
            "delay_ms": 100
          }
        ]
      }
    },
    "moonfly_r_arm": {
      "loop": false,
      "directions": {
        "south": [
          {
            "x": 0,
            "y": 476,
            "w": 45,
            "h": 34,
            "delay_ms": 100
          }
        ],
        "north": [
          {
            "x": 45,
            "y": 476,
            "w": 45,
            "h": 34,
            "delay_ms": 100
          }
        ],
        "east": [
          {
            "x": 90,
            "y": 476,
            "w": 45,
            "h": 34,
            "delay_ms": 100
          }
        ],
        "west": [
          {
            "x": 135,
            "y": 476,
            "w": 45,
            "h": 34,
            "delay_ms": 100
          }
        ]
      }
    },
    "moonfly_l_arm": {
      "loop": false,
      "directions": {
        "south": [
          {
            "x": 180,
            "y": 476,
            "w": 45,
            "h": 34,
            "delay_ms": 100
          }
        ],
        "north": [
          {
            "x": 225,
            "y": 476,
            "w": 45,
            "h": 34,
            "delay_ms": 100
          }
        ],
        "east": [
          {
            "x": 270,
            "y": 476,
            "w": 45,
            "h": 34,
            "delay_ms": 100
          }
        ],
        "west": [
          {
            "x": 315,
            "y": 476,
            "w": 45,
            "h": 34,
            "delay_ms": 100
          }
        ]
      }
    },
    "moonfly_r_leg": {
      "loop": false,
      "directions": {
        "south": [
          {
            "x": 360,
            "y": 476,
            "w": 45,
            "h": 34,
            "delay_ms": 100
          }
        ],
        "north": [
          {
            "x": 405,
            "y": 476,
            "w": 45,
            "h": 34,
            "delay_ms": 100
          }
        ],
        "east": [
          {
            "x": 450,
            "y": 476,
            "w": 45,
            "h": 34,
            "delay_ms": 100
          }
        ],
        "west": [
          {
            "x": 495,
            "y": 476,
            "w": 45,
            "h": 34,
            "delay_ms": 100
          }
        ]
      }
    },
    "moonfly_l_leg": {
      "loop": false,
      "directions": {
        "south": [
          {
            "x": 540,
            "y": 476,
            "w": 45,
            "h": 34,
            "delay_ms": 100
          }
        ],
        "north": [
          {
            "x": 585,
            "y": 476,
            "w": 45,
            "h": 34,
            "delay_ms": 100
          }
        ],
        "east": [
          {
            "x": 630,
            "y": 476,
            "w": 45,
            "h": 34,
            "delay_ms": 100
          }
        ],
        "west": [
          {
            "x": 675,
            "y": 476,
            "w": 45,
            "h": 34,
            "delay_ms": 100
          }
        ]
      }
    },
    "oakworm_head": {
      "loop": false,
      "directions": {
        "south": [
          {
            "x": 0,
            "y": 510,
            "w": 45,
            "h": 34,
            "delay_ms": 100
          }
        ],
        "north": [
          {
            "x": 45,
            "y": 510,
            "w": 45,
            "h": 34,
            "delay_ms": 100
          }
        ],
        "east": [
          {
            "x": 90,
            "y": 510,
            "w": 45,
            "h": 34,
            "delay_ms": 100
          }
        ],
        "west": [
          {
            "x": 135,
            "y": 510,
            "w": 45,
            "h": 34,
            "delay_ms": 100
          }
        ]
      }
    },
    "oakworm_chest": {
      "loop": false,
      "directions": {
        "south": [
          {
            "x": 180,
            "y": 510,
            "w": 45,
            "h": 34,
            "delay_ms": 100
          }
        ],
        "north": [
          {
            "x": 225,
            "y": 510,
            "w": 45,
            "h": 34,
            "delay_ms": 100
          }
        ],
        "east": [
          {
            "x": 270,
            "y": 510,
            "w": 45,
            "h": 34,
            "delay_ms": 100
          }
        ],
        "west": [
          {
            "x": 315,
            "y": 510,
            "w": 45,
            "h": 34,
            "delay_ms": 100
          }
        ]
      }
    },
    "oakworm_r_arm": {
      "loop": false,
      "directions": {
        "south": [
          {
            "x": 360,
            "y": 510,
            "w": 45,
            "h": 34,
            "delay_ms": 100
          }
        ],
        "north": [
          {
            "x": 405,
            "y": 510,
            "w": 45,
            "h": 34,
            "delay_ms": 100
          }
        ],
        "east": [
          {
            "x": 450,
            "y": 510,
            "w": 45,
            "h": 34,
            "delay_ms": 100
          }
        ],
        "west": [
          {
            "x": 495,
            "y": 510,
            "w": 45,
            "h": 34,
            "delay_ms": 100
          }
        ]
      }
    },
    "oakworm_l_arm": {
      "loop": false,
      "directions": {
        "south": [
          {
            "x": 540,
            "y": 510,
            "w": 45,
            "h": 34,
            "delay_ms": 100
          }
        ],
        "north": [
          {
            "x": 585,
            "y": 510,
            "w": 45,
            "h": 34,
            "delay_ms": 100
          }
        ],
        "east": [
          {
            "x": 630,
            "y": 510,
            "w": 45,
            "h": 34,
            "delay_ms": 100
          }
        ],
        "west": [
          {
            "x": 675,
            "y": 510,
            "w": 45,
            "h": 34,
            "delay_ms": 100
          }
        ]
      }
    },
    "oakworm_r_leg": {
      "loop": false,
      "directions": {
        "south": [
          {
            "x": 0,
            "y": 544,
            "w": 45,
            "h": 34,
            "delay_ms": 100
          }
        ],
        "north": [
          {
            "x": 45,
            "y": 544,
            "w": 45,
            "h": 34,
            "delay_ms": 100
          }
        ],
        "east": [
          {
            "x": 90,
            "y": 544,
            "w": 45,
            "h": 34,
            "delay_ms": 100
          }
        ],
        "west": [
          {
            "x": 135,
            "y": 544,
            "w": 45,
            "h": 34,
            "delay_ms": 100
          }
        ]
      }
    },
    "oakworm_l_leg": {
      "loop": false,
      "directions": {
        "south": [
          {
            "x": 180,
            "y": 544,
            "w": 45,
            "h": 34,
            "delay_ms": 100
          }
        ],
        "north": [
          {
            "x": 225,
            "y": 544,
            "w": 45,
            "h": 34,
            "delay_ms": 100
          }
        ],
        "east": [
          {
            "x": 270,
            "y": 544,
            "w": 45,
            "h": 34,
            "delay_ms": 100
          }
        ],
        "west": [
          {
            "x": 315,
            "y": 544,
            "w": 45,
            "h": 34,
            "delay_ms": 100
          }
        ]
      }
    },
    "jungle_head": {
      "loop": false,
      "directions": {
        "south": [
          {
            "x": 360,
            "y": 544,
            "w": 45,
            "h": 34,
            "delay_ms": 100
          }
        ],
        "north": [
          {
            "x": 405,
            "y": 544,
            "w": 45,
            "h": 34,
            "delay_ms": 100
          }
        ],
        "east": [
          {
            "x": 450,
            "y": 544,
            "w": 45,
            "h": 34,
            "delay_ms": 100
          }
        ],
        "west": [
          {
            "x": 495,
            "y": 544,
            "w": 45,
            "h": 34,
            "delay_ms": 100
          }
        ]
      }
    },
    "jungle_chest": {
      "loop": false,
      "directions": {
        "south": [
          {
            "x": 540,
            "y": 544,
            "w": 45,
            "h": 34,
            "delay_ms": 100
          }
        ],
        "north": [
          {
            "x": 585,
            "y": 544,
            "w": 45,
            "h": 34,
            "delay_ms": 100
          }
        ],
        "east": [
          {
            "x": 630,
            "y": 544,
            "w": 45,
            "h": 34,
            "delay_ms": 100
          }
        ],
        "west": [
          {
            "x": 675,
            "y": 544,
            "w": 45,
            "h": 34,
            "delay_ms": 100
          }
        ]
      }
    },
    "jungle_r_arm": {
      "loop": false,
      "directions": {
        "south": [
          {
            "x": 0,
            "y": 578,
            "w": 45,
            "h": 34,
            "delay_ms": 100
          }
        ],
        "north": [
          {
            "x": 45,
            "y": 578,
            "w": 45,
            "h": 34,
            "delay_ms": 100
          }
        ],
        "east": [
          {
            "x": 90,
            "y": 578,
            "w": 45,
            "h": 34,
            "delay_ms": 100
          }
        ],
        "west": [
          {
            "x": 135,
            "y": 578,
            "w": 45,
            "h": 34,
            "delay_ms": 100
          }
        ]
      }
    },
    "jungle_l_arm": {
      "loop": false,
      "directions": {
        "south": [
          {
            "x": 180,
            "y": 578,
            "w": 45,
            "h": 34,
            "delay_ms": 100
          }
        ],
        "north": [
          {
            "x": 225,
            "y": 578,
            "w": 45,
            "h": 34,
            "delay_ms": 100
          }
        ],
        "east": [
          {
            "x": 270,
            "y": 578,
            "w": 45,
            "h": 34,
            "delay_ms": 100
          }
        ],
        "west": [
          {
            "x": 315,
            "y": 578,
            "w": 45,
            "h": 34,
            "delay_ms": 100
          }
        ]
      }
    },
    "jungle_r_leg": {
      "loop": false,
      "directions": {
        "south": [
          {
            "x": 360,
            "y": 578,
            "w": 45,
            "h": 34,
            "delay_ms": 100
          }
        ],
        "north": [
          {
            "x": 405,
            "y": 578,
            "w": 45,
            "h": 34,
            "delay_ms": 100
          }
        ],
        "east": [
          {
            "x": 450,
            "y": 578,
            "w": 45,
            "h": 34,
            "delay_ms": 100
          }
        ],
        "west": [
          {
            "x": 495,
            "y": 578,
            "w": 45,
            "h": 34,
            "delay_ms": 100
          }
        ]
      }
    },
    "jungle_l_leg": {
      "loop": false,
      "directions": {
        "south": [
          {
            "x": 540,
            "y": 578,
            "w": 45,
            "h": 34,
            "delay_ms": 100
          }
        ],
        "north": [
          {
            "x": 585,
            "y": 578,
            "w": 45,
            "h": 34,
            "delay_ms": 100
          }
        ],
        "east": [
          {
            "x": 630,
            "y": 578,
            "w": 45,
            "h": 34,
            "delay_ms": 100
          }
        ],
        "west": [
          {
            "x": 675,
            "y": 578,
            "w": 45,
            "h": 34,
            "delay_ms": 100
          }
        ]
      }
    },
    "witchwing_head": {
      "loop": false,
      "directions": {
        "south": [
          {
            "x": 0,
            "y": 612,
            "w": 45,
            "h": 34,
            "delay_ms": 100
          }
        ],
        "north": [
          {
            "x": 45,
            "y": 612,
            "w": 45,
            "h": 34,
            "delay_ms": 100
          }
        ],
        "east": [
          {
            "x": 90,
            "y": 612,
            "w": 45,
            "h": 34,
            "delay_ms": 100
          }
        ],
        "west": [
          {
            "x": 135,
            "y": 612,
            "w": 45,
            "h": 34,
            "delay_ms": 100
          }
        ]
      }
    },
    "witchwing_chest": {
      "loop": false,
      "directions": {
        "south": [
          {
            "x": 180,
            "y": 612,
            "w": 45,
            "h": 34,
            "delay_ms": 100
          }
        ],
        "north": [
          {
            "x": 225,
            "y": 612,
            "w": 45,
            "h": 34,
            "delay_ms": 100
          }
        ],
        "east": [
          {
            "x": 270,
            "y": 612,
            "w": 45,
            "h": 34,
            "delay_ms": 100
          }
        ],
        "west": [
          {
            "x": 315,
            "y": 612,
            "w": 45,
            "h": 34,
            "delay_ms": 100
          }
        ]
      }
    },
    "witchwing_r_arm": {
      "loop": false,
      "directions": {
        "south": [
          {
            "x": 360,
            "y": 612,
            "w": 45,
            "h": 34,
            "delay_ms": 100
          }
        ],
        "north": [
          {
            "x": 405,
            "y": 612,
            "w": 45,
            "h": 34,
            "delay_ms": 100
          }
        ],
        "east": [
          {
            "x": 450,
            "y": 612,
            "w": 45,
            "h": 34,
            "delay_ms": 100
          }
        ],
        "west": [
          {
            "x": 495,
            "y": 612,
            "w": 45,
            "h": 34,
            "delay_ms": 100
          }
        ]
      }
    },
    "witchwing_l_arm": {
      "loop": false,
      "directions": {
        "south": [
          {
            "x": 540,
            "y": 612,
            "w": 45,
            "h": 34,
            "delay_ms": 100
          }
        ],
        "north": [
          {
            "x": 585,
            "y": 612,
            "w": 45,
            "h": 34,
            "delay_ms": 100
          }
        ],
        "east": [
          {
            "x": 630,
            "y": 612,
            "w": 45,
            "h": 34,
            "delay_ms": 100
          }
        ],
        "west": [
          {
            "x": 675,
            "y": 612,
            "w": 45,
            "h": 34,
            "delay_ms": 100
          }
        ]
      }
    },
    "witchwing_r_leg": {
      "loop": false,
      "directions": {
        "south": [
          {
            "x": 0,
            "y": 646,
            "w": 45,
            "h": 34,
            "delay_ms": 100
          }
        ],
        "north": [
          {
            "x": 45,
            "y": 646,
            "w": 45,
            "h": 34,
            "delay_ms": 100
          }
        ],
        "east": [
          {
            "x": 90,
            "y": 646,
            "w": 45,
            "h": 34,
            "delay_ms": 100
          }
        ],
        "west": [
          {
            "x": 135,
            "y": 646,
            "w": 45,
            "h": 34,
            "delay_ms": 100
          }
        ]
      }
    },
    "witchwing_l_leg": {
      "loop": false,
      "directions": {
        "south": [
          {
            "x": 180,
            "y": 646,
            "w": 45,
            "h": 34,
            "delay_ms": 100
          }
        ],
        "north": [
          {
            "x": 225,
            "y": 646,
            "w": 45,
            "h": 34,
            "delay_ms": 100
          }
        ],
        "east": [
          {
            "x": 270,
            "y": 646,
            "w": 45,
            "h": 34,
            "delay_ms": 100
          }
        ],
        "west": [
          {
            "x": 315,
            "y": 646,
            "w": 45,
            "h": 34,
            "delay_ms": 100
          }
        ]
      }
    },
    "lovers_head": {
      "loop": false,
      "directions": {
        "south": [
          {
            "x": 360,
            "y": 646,
            "w": 45,
            "h": 34,
            "delay_ms": 100
          }
        ],
        "north": [
          {
            "x": 405,
            "y": 646,
            "w": 45,
            "h": 34,
            "delay_ms": 100
          }
        ],
        "east": [
          {
            "x": 450,
            "y": 646,
            "w": 45,
            "h": 34,
            "delay_ms": 100
          }
        ],
        "west": [
          {
            "x": 495,
            "y": 646,
            "w": 45,
            "h": 34,
            "delay_ms": 100
          }
        ]
      }
    },
    "lovers_chest": {
      "loop": false,
      "directions": {
        "south": [
          {
            "x": 540,
            "y": 646,
            "w": 45,
            "h": 34,
            "delay_ms": 100
          }
        ],
        "north": [
          {
            "x": 585,
            "y": 646,
            "w": 45,
            "h": 34,
            "delay_ms": 100
          }
        ],
        "east": [
          {
            "x": 630,
            "y": 646,
            "w": 45,
            "h": 34,
            "delay_ms": 100
          }
        ],
        "west": [
          {
            "x": 675,
            "y": 646,
            "w": 45,
            "h": 34,
            "delay_ms": 100
          }
        ]
      }
    },
    "lovers_r_arm": {
      "loop": false,
      "directions": {
        "south": [
          {
            "x": 0,
            "y": 680,
            "w": 45,
            "h": 34,
            "delay_ms": 100
          }
        ],
        "north": [
          {
            "x": 45,
            "y": 680,
            "w": 45,
            "h": 34,
            "delay_ms": 100
          }
        ],
        "east": [
          {
            "x": 90,
            "y": 680,
            "w": 45,
            "h": 34,
            "delay_ms": 100
          }
        ],
        "west": [
          {
            "x": 135,
            "y": 680,
            "w": 45,
            "h": 34,
            "delay_ms": 100
          }
        ]
      }
    },
    "lovers_l_arm": {
      "loop": false,
      "directions": {
        "south": [
          {
            "x": 180,
            "y": 680,
            "w": 45,
            "h": 34,
            "delay_ms": 100
          }
        ],
        "north": [
          {
            "x": 225,
            "y": 680,
            "w": 45,
            "h": 34,
            "delay_ms": 100
          }
        ],
        "east": [
          {
            "x": 270,
            "y": 680,
            "w": 45,
            "h": 34,
            "delay_ms": 100
          }
        ],
        "west": [
          {
            "x": 315,
            "y": 680,
            "w": 45,
            "h": 34,
            "delay_ms": 100
          }
        ]
      }
    },
    "lovers_r_leg": {
      "loop": false,
      "directions": {
        "south": [
          {
            "x": 360,
            "y": 680,
            "w": 45,
            "h": 34,
            "delay_ms": 100
          }
        ],
        "north": [
          {
            "x": 405,
            "y": 680,
            "w": 45,
            "h": 34,
            "delay_ms": 100
          }
        ],
        "east": [
          {
            "x": 450,
            "y": 680,
            "w": 45,
            "h": 34,
            "delay_ms": 100
          }
        ],
        "west": [
          {
            "x": 495,
            "y": 680,
            "w": 45,
            "h": 34,
            "delay_ms": 100
          }
        ]
      }
    },
    "lovers_l_leg": {
      "loop": false,
      "directions": {
        "south": [
          {
            "x": 540,
            "y": 680,
            "w": 45,
            "h": 34,
            "delay_ms": 100
          }
        ],
        "north": [
          {
            "x": 585,
            "y": 680,
            "w": 45,
            "h": 34,
            "delay_ms": 100
          }
        ],
        "east": [
          {
            "x": 630,
            "y": 680,
            "w": 45,
            "h": 34,
            "delay_ms": 100
          }
        ],
        "west": [
          {
            "x": 675,
            "y": 680,
            "w": 45,
            "h": 34,
            "delay_ms": 100
          }
        ]
      }
    }
  }
}